lazylicense/__init__.py
lazylicense/__main__.py
lazylicense/lazylicense.py
lazylicense/utils/__init__.py
lazylicense/utils/file_scanner.py
lazylicense/utils/read_write.py
lazylicense-0.1.1.dist-info/LICENSE
lazylicense-0.1.1.dist-info/METADATA
lazylicense-0.1.1.dist-info/WHEEL
lazylicense-0.1.1.dist-info/top_level.txt
lazylicense-0.1.1.dist-info/RECORD
