Metadata-Version: 2.1
Name: lazylicense
Version: 0.1.1
Summary: Python package for adding Apache v2.0 license for source files.
Home-page: https://github.com/oddaspa/lazylicense
Author: Odd Gunnar Aspaas
Author-email: odd.gunnar.aspaas@gmail.com
License: UNKNOWN
Project-URL: Bug Tracker, https://github.com/oddaspa/lazylicense/issues
Platform: UNKNOWN
Classifier: Programming Language :: Python :: 3
Classifier: License :: OSI Approved :: MIT License
Classifier: Operating System :: OS Independent
Requires-Python: >=3.6
License-File: LICENSE
